igloo_mcp/__init__.py
igloo_mcp/cache/__init__.py
igloo_mcp/cache/query_result_cache.py
igloo_mcp/catalog/__init__.py
igloo_mcp/catalog/catalog_service.py
igloo_mcp/catalog/index.py
igloo_mcp/circuit_breaker.py
igloo_mcp/cli.py
igloo_mcp/config.py
igloo_mcp/constants.py
igloo_mcp/context.py
igloo_mcp/dependency/__init__.py
igloo_mcp/dependency/dependency_service.py
igloo_mcp/error_handling.py
igloo_mcp/living_reports/__init__.py
igloo_mcp/living_reports/changes_schema.py
igloo_mcp/living_reports/history_index.py
igloo_mcp/living_reports/index.py
igloo_mcp/living_reports/merge_utils.py
igloo_mcp/living_reports/models.py
igloo_mcp/living_reports/quarto_renderer.py
igloo_mcp/living_reports/renderers/__init__.py
igloo_mcp/living_reports/renderers/html_standalone.py
igloo_mcp/living_reports/renderers/markdown.py
igloo_mcp/living_reports/schema_constants.py
igloo_mcp/living_reports/selector.py
igloo_mcp/living_reports/service.py
igloo_mcp/living_reports/storage.py
igloo_mcp/living_reports/templates/__init__.py
igloo_mcp/living_reports/templates/report.qmd.j2
igloo_mcp/living_reports/templates/styles.css
igloo_mcp/living_reports/templates.py
igloo_mcp/logging/__init__.py
igloo_mcp/logging/query_history.py
igloo_mcp/mcp/__init__.py
igloo_mcp/mcp/error_utils.py
igloo_mcp/mcp/exceptions.py
igloo_mcp/mcp/tools/__init__.py
igloo_mcp/mcp/tools/base.py
igloo_mcp/mcp/tools/build_catalog.py
igloo_mcp/mcp/tools/build_dependency_graph.py
igloo_mcp/mcp/tools/create_report.py
igloo_mcp/mcp/tools/evolve_report.py
igloo_mcp/mcp/tools/evolve_report_batch.py
igloo_mcp/mcp/tools/execute_query.py
igloo_mcp/mcp/tools/get_catalog_summary.py
igloo_mcp/mcp/tools/get_report.py
igloo_mcp/mcp/tools/get_report_schema.py
igloo_mcp/mcp/tools/health.py
igloo_mcp/mcp/tools/render_report.py
igloo_mcp/mcp/tools/schema_utils.py
igloo_mcp/mcp/tools/search_catalog.py
igloo_mcp/mcp/tools/search_citations.py
igloo_mcp/mcp/tools/search_report.py
igloo_mcp/mcp/tools/test_connection.py
igloo_mcp-0.4.2.dist-info/WHEEL
igloo_mcp-0.4.2.dist-info/entry_points.txt
igloo_mcp-0.4.2.dist-info/METADATA
igloo_mcp-0.4.2.dist-info/RECORD
