Metadata-Version: 2.3
Name: igloo-mcp
Version: 0.4.2
Summary: Igloo MCP - Snowflake MCP Server for agentic native workflows
Keywords: snowflake,mcp,ai,data,analytics,model-context-protocol
Author: Evan Kim
Author-email: Evan Kim <ekcopersonal@gmail.com>
Requires-Dist: rich>=13.0.0
Requires-Dist: pyyaml>=6.0.0
Requires-Dist: snowflake-cli>=2.0.0
Requires-Dist: sqlglot>=27.16.3
Requires-Dist: pyjwt>=2.9.0
Requires-Dist: pyvis>=0.3.2
Requires-Dist: networkx>=3.0
Requires-Dist: websockets>=15.0.1
Requires-Dist: mcp>=1.0.0
Requires-Dist: fastmcp>=2.8.1
Requires-Dist: snowflake-labs-mcp>=1.3.3
Requires-Dist: pydantic>=2.7.0
Requires-Dist: jinja2>=3.1.0
Requires-Dist: markdown>=3.5,<4.0
Requires-Python: >=3.12, <3.14
Project-URL: Documentation, https://github.com/Evan-Kim2028/igloo-mcp#readme
Project-URL: Homepage, https://github.com/Evan-Kim2028/igloo-mcp
Project-URL: Repository, https://github.com/Evan-Kim2028/igloo-mcp
